ocs_academic_hub/__init__.py
ocs_academic_hub/access.py
ocs_academic_hub/datahub.py
ocs_academic_hub/hub_datasets.json
ocs_academic_hub/learning.py
ocs_academic_hub/ocs_academic_hub.py
ocs_academic_hub/queries.py
ocs_academic_hub/util.py
ocs_academic_hub-1.0.1.dist-info/LICENSE
ocs_academic_hub-1.0.1.dist-info/METADATA
ocs_academic_hub-1.0.1.dist-info/WHEEL
ocs_academic_hub-1.0.1.dist-info/top_level.txt
ocs_academic_hub-1.0.1.dist-info/RECORD
