Metadata-Version: 2.1
Name: ocs-academic-hub
Version: 1.0.1
Summary: Academic Hub Library
Home-page: https://github.com/cfoisy-osisoft/academic-hub
Author: Christian Foisy
Author-email: christian.foisy@aveva.com
License: UNKNOWN
Project-URL: Bug Tracker, https://github.com/cfoisy-osisoft/academic-hub/issues
Platform: UNKNOWN
Classifier: Programming Language :: Python :: 3
Classifier: License :: OSI Approved :: Apache Software License
Classifier: Operating System :: OS Independent
Requires-Python: >=3.6
License-File: LICENSE
Requires-Dist: pandas (>=0.24.2)
Requires-Dist: ocs-sample-library-hub (>=0.1.19)
Requires-Dist: numpy
Requires-Dist: python-dateutil (>=2.8.0)
Requires-Dist: typeguard (>=2.4.1)
Requires-Dist: requests (>=2.26)
Requires-Dist: gql (==2.0.0)
Requires-Dist: backoff
Requires-Dist: markdown
Requires-Dist: importlib-metadata
Requires-Dist: ipywidgets
